calc/__init__.py
calc/__main__.py
calc/dscalc.py
dscalc-0.0.1.dist-info/METADATA
dscalc-0.0.1.dist-info/WHEEL
dscalc-0.0.1.dist-info/entry_points.txt
dscalc-0.0.1.dist-info/top_level.txt
dscalc-0.0.1.dist-info/RECORD
