Metadata-Version: 2.1
Name: dscalc
Version: 0.0.1
Summary: Perform basic calculations
Author-email: Deepak Singh <info@info.com>
Project-URL: Homepage, https://github.com/deepsAI8/sample_package
Keywords: ds,calc,calculator
Classifier: License :: OSI Approved :: MIT License
Classifier: Programming Language :: Python
Classifier: Programming Language :: Python :: 3
Requires-Python: >=3.9
Requires-Dist: tomli ; python_version < "3.11"
Provides-Extra: dev
Requires-Dist: bumpver ; extra == 'dev'
Requires-Dist: pip-tools ; extra == 'dev'
Requires-Dist: pytest ; extra == 'dev'
